README.rst
setup.py
paperwrap/__init__.py
paperwrap/cli.py
paperwrap/models.py
paperwrap/utils.py
paperwrap/wrapper.py
paperwrap.egg-info/PKG-INFO
paperwrap.egg-info/SOURCES.txt
paperwrap.egg-info/dependency_links.txt
paperwrap.egg-info/entry_points.txt
paperwrap.egg-info/requires.txt
paperwrap.egg-info/top_level.txt
test/test_cli.py
test/test_data.py
test/test_models.py
test/test_wrapper.py