Metadata-Version: 1.1
Name: paperwrap
Version: 0.14.3
Summary: API Wrapper and command line client forthe open-source note taking tool paperwork
Home-page: https://github.com/ntnn/paperwork.py
Author: Nelo Wallus
Author-email: wallus.nelo@gmail.com
License: MIT
Keywords: paperwork rocks twostairs api wrapper paperwrap
Platform: UNKNOWN
Classifier: Development Status :: 3 - Alpha
Classifier: Intended Audience :: Developers
Classifier: License :: OSI Approved :: MIT License
Classifier: Programming Language :: Python :: 2.7
Classifier: Programming Language :: Python :: 3.3
Classifier: Programming Language :: Python :: 3.4
